drslib/__init__.py
drslib/banner.py
drslib/cli_ui.py
drslib/debug.py
drslib/decorators.py
drslib/dict_utils.py
drslib/execute.py
drslib/fsdb.py
drslib/hash.py
drslib/interval.py
drslib/list_utils.py
drslib/mediainfo.py
drslib/multiprocessing.py
drslib/os_detect.py
drslib/path_tools.py
drslib/py.typed
drslib/spinner.py
drslib/str_utils.py
drslib/stream.py
drslib/utils.py
drslib/web_crawl.py
DRSlib_DavidRodriguezSoaresCUI-0.10.1.dist-info/LICENSE
DRSlib_DavidRodriguezSoaresCUI-0.10.1.dist-info/METADATA
DRSlib_DavidRodriguezSoaresCUI-0.10.1.dist-info/WHEEL
DRSlib_DavidRodriguezSoaresCUI-0.10.1.dist-info/top_level.txt
DRSlib_DavidRodriguezSoaresCUI-0.10.1.dist-info/RECORD
