Metadata-Version: 2.1
Name: DRSlib-DavidRodriguezSoaresCUI
Version: 0.10.1
Summary: DRSlib - a set of utilities by DavidRodriguezSoaresCUI
Home-page: https://github.com/DavidRodriguezSoaresCUI/DRSlib
Author: DavidRodriguezSoaresCUI
Author-email: fireblaze904+DRSlib@gmail.com
Project-URL: Bug Tracker, https://github.com/DavidRodriguezSoaresCUI/DRSlib/issues
Classifier: Intended Audience :: Developers
Classifier: License :: CC0 1.0 Universal (CC0 1.0) Public Domain Dedication
Classifier: Operating System :: OS Independent
Classifier: Programming Language :: Python :: 3 :: Only
Classifier: Programming Language :: Python :: 3.7
Classifier: Programming Language :: Python :: 3.8
Classifier: Programming Language :: Python :: 3.9
Classifier: Topic :: Software Development :: Libraries :: Python Modules
Requires-Python: >=3.7
License-File: LICENSE
Requires-Dist: numpy
Requires-Dist: psutil
Requires-Dist: send2trash
